napari_ndtiffs/__init__.py
napari_ndtiffs/_cupy_affine.py
napari_ndtiffs/_ocl_affine.py
napari_ndtiffs/affine.py
napari_ndtiffs/napari.yaml
napari_ndtiffs/reader.py
napari_ndtiffs/settingstxt.py
napari_ndtiffs-0.2.1.dist-info/METADATA
napari_ndtiffs-0.2.1.dist-info/WHEEL
napari_ndtiffs-0.2.1.dist-info/entry_points.txt
napari_ndtiffs-0.2.1.dist-info/licenses/LICENSE
napari_ndtiffs-0.2.1.dist-info/RECORD
