Metadata-Version: 2.1
Name: napari-ndtiffs
Version: 0.2.1
Summary: napari plugin for nd tiff folders with OpenCl deskew
Project-URL: Bug Tracker, https://github.com/tlambert03/napari-ndtiffs/issues
Project-URL: Documentation, https://github.com/tlambert03/napari-ndtiffs#README.md
Project-URL: Source Code, https://github.com/tlambert03/napari-ndtiffs
Project-URL: User Support, https://github.com/tlambert03/napari-ndtiffs/issues
Author-email: Talley Lambert <talley.lambert@gmail.com>
License: BSD-3-Clause
License-File: LICENSE
Classifier: Development Status :: 3 - Alpha
Classifier: Framework :: napari
Classifier: Intended Audience :: Developers
Classifier: License :: OSI Approved :: BSD License
Classifier: Programming Language :: Python :: 3
Classifier: Programming Language :: Python :: 3.8
Classifier: Programming Language :: Python :: 3.9
Classifier: Programming Language :: Python :: 3.10
Requires-Python: >=3.8
Requires-Dist: dask[array]
Requires-Dist: napari-plugin-engine>=0.1.4
Requires-Dist: numpy
Requires-Dist: python-dateutil
Requires-Dist: scipy
Requires-Dist: tifffile
Provides-Extra: dev
Requires-Dist: black; extra == 'dev'
Requires-Dist: ipython; extra == 'dev'
Requires-Dist: mypy; extra == 'dev'
Requires-Dist: pdbpp; extra == 'dev'
Requires-Dist: rich; extra == 'dev'
Requires-Dist: ruff; extra == 'dev'
Provides-Extra: opencl
Requires-Dist: pyopencl; extra == 'opencl'
Provides-Extra: test
Requires-Dist: pyopencl; extra == 'test'
Requires-Dist: pytest; extra == 'test'
Requires-Dist: pytest-cov; extra == 'test'
